{
  "$schema": "https://developer.microsoft.com/json-schemas/fabric/item/report/definition/visualContainer/2.4.0/schema.json",
  "name": "GenAI_Visual_5_816a36",
  "position": {
    "x": 20,
    "y": 460,
    "z": 0,
    "width": 610,
    "height": 240,
    "tabOrder": 4
  },
  "visual": {
    "visualType": "pieChart",
    "query": {
      "queryState": {
        "Category": {
          "projections": [
            {
              "field": {
                "Column": {
                  "Expression": {
                    "SourceRef": {
                      "Entity": "customers_rows"
                    }
                  },
                  "Property": "region"
                }
              },
              "queryRef": "customers_rows.region",
              "nativeQueryRef": "Region",
              "displayName": "Region",
              "active": true
            }
          ]
        },
        "Y": {
          "projections": [
            {
              "field": {
                "Aggregation": {
                  "Expression": {
                    "Column": {
                      "Expression": {
                        "SourceRef": {
                          "Entity": "order_items_rows"
                        }
                      },
                      "Property": "quantity"
                    }
                  },
                  "Function": 0
                }
              },
              "queryRef": "Sum(order_items_rows.quantity)",
              "nativeQueryRef": "Quantity",
              "displayName": "Quantity"
            }
          ]
        }
      },
      "sortDefinition": {
        "sort": [
          {
            "field": {
              "Aggregation": {
                "Expression": {
                  "Column": {
                    "Expression": {
                      "SourceRef": {
                        "Entity": "order_items_rows"
                      }
                    },
                    "Property": "quantity"
                  }
                },
                "Function": 0
              }
            },
            "direction": "Descending"
          }
        ],
        "isDefaultSort": true
      }
    },
    "visualContainerObjects": {
      "title": [
        {
          "properties": {
            "text": {
              "expr": {
                "Literal": {
                  "Value": "'Regional Revenue Breakdown'"
                }
              }
            },
            "show": {
              "expr": {
                "Literal": {
                  "Value": "true"
                }
              }
            },
            "alignment": {
              "expr": {
                "Literal": {
                  "Value": "'center'"
                }
              }
            }
          }
        }
      ]
    },
    "drillFilterOtherVisuals": true
  }
}